{
  "preRequisites:11": [
    30160
  ],
  "properties:10": {
    "betterquesting:10": {
      "desc:8": "§6ME Drive§f\\n\\n§aHolds up to 10 storage cells in one block.§f\\n\\nThe §bME Drive§f is a block that holds up to §e10 storage cells§f. It connects to the ME network and provides storage from the inserted cells.\\n\\n§6Specifications§f:\\n§b•§f Cell slots: §e10§f\\n§b•§f LED indicators: §9color-coded cell status§f\\n§b•§f Compatible with all §bStorage Cell§f types (1k, 4k, 16k, 64k, fluid, gas)\\n§b•§f No channel cost\\n\\n§6How to Use§f:\\n§b1.§f Place the Drive on a cable\\n§b2.§f Insert storage cells into the slots\\n§b3.§f The cells' contents become accessible network-wide\\n\\n§6LED Color Meanings§f:\\n§b•§f Green: cell has content\\n§b•§f Orange: cell is full\\n§b•§f Blue: cell is empty\\n§b•§f Red: cell is partitioned / locked\\n\\n§6Crafting Recipe§f:\\n§b•§f §b2× Engineering Processor§f\\n§b•§f §b2× Fluix Glass Cable§f\\n§b•§f §b2× Iron Ingot§f\\n\\n§6Strategic Role§f:\\nThe §bME Drive§f is the §9main storage component§f of any AE2 network. Build multiple drives in a §bstorage room§f for scalability.\\n",
      "icon:10": {
        "Count:3": 1,
        "id:8": "appliedenergistics2:drive",
        "OreDict:8": ""
      },
      "name:8": "ME Drive",
      "visibility:8": "ALWAYS"
    }
  },
  "questID:3": 30161,
  "rewards:9": {},
  "tasks:9": {
    "0:10": {
      "autoConsume:1": 0,
      "consume:1": 0,
      "groupDetect:1": 0,
      "ignoreNBT:1": 0,
      "index:3": 0,
      "partialMatch:1": 0,
      "requiredItems:9": {
        "0:10": {
          "Count:3": 1,
          "id:8": "appliedenergistics2:drive",
          "OreDict:8": ""
        }
      },
      "taskID:8": "bq_standard:retrieval"
    }
  }
}
