{
  "preRequisites:11": [
    30160
  ],
  "properties:10": {
    "betterquesting:10": {
      "desc:8": "§6P2P Tunnels§f:\nThe §6P2P Tunnels §f(appliedenergistics2:part:460) are §ecable parts §f that §btransparently connect §f any two networks of compatible types. They are the §6power-distance §f and §6cable-extension §f solution for AE2 networks.\n\n§6Production Path (network/parts/tunnels_me.json)§f:\nPattern \" a / aba / ccc\":\n- §ba§f: §6Iron Ingot §f(ingotIron) — 4 (top + middle corners)\n- §bb§f: §6Engineering Processor §f(appliedenergistics2:material:24) — 1 (middle centre)\n- §cc§f: §6Fluix Crystal §f(any crystal in the §6#appliedenergistics2:fluixCrystal §foredict tag) — 3 (bottom row)\n- Yields 1× ME P2P Tunnel\n\n§6P2P Tunnel Family§f:\n- §bME P2P Tunnel §f(appliedenergistics2:part:460) — connects two §6ME networks §f\n- §bItem P2P Tunnel §f(variants) — connect §6item §f I/O\n- §bFluid P2P Tunnel §f(variants) — connect §6fluid §f I/O\n- §bRedstone P2P Tunnel §f — relays §bredstone signals §f\n- §bFE P2P Tunnel §f — relays §6Forge Energy §f (RF/Tesla)\n- §bEU P2P Tunnel §f — relays §6EU §f (IC2)\n- §bLight P2P Tunnel §f — relays §6light updates §f\n\n§6Function (PartP2PTunnelME.java:53-225)§f:\n- §bNetwork bridging §f: place two P2P tunnels of the same type on §bseparate §fME networks; they automatically pair\n- §bTransparent transport §f: items, fluids, power, and redstone flow through the tunnels as if the networks were directly connected\n- §bCompressed channel §f: an ME P2P Tunnel uses §b1 channel §f on each side; with §6Dense Cable §f, it carries §b32 channels §f of payload\n- §bTunnel cost §f: each P2P tunnel has an §bouter proxy §f and an §binner proxy §f (PartP2PTunnelME.java:67-68), consuming §bcable channels §f\n- §bFrequency §f: each tunnel has §b1-5 §f frequency slots; matching frequencies pair up\n\n§6Direct Descendants (TaskRetrieval graph)§f:\nThe jei-graph shows 0 items the P2P Tunnel is a component of, but it is referenced in 1,250 §6use sites §f across the mod pack. Common uses:\n- §bLong-distance networks §f: place one P2P on each end of a long cable run\n- §bWireless extension §f: pair P2P with a §6Wireless Access Point §f for cross-network routing\n- §bMultinetwork setups §f: P2P is the only way to have two §6logically separate §f networks exchange items\n\n§6Practical Use§f:\n- §eTip§f: number your P2P tunnels with §6coloured dyes §f to keep track of pairings\n- §eTip§f: a P2P tunnel consumes §b0 AE/t §f at idle, but its endpoints do consume channels from the parent cables\n- §cWarning§f: P2P tunnels do §cnot §f work across §bchunk loads §f unless both ends are in §6loaded §f chunks\n- §cWarning§f: an ME P2P tunnel on a §cbroken §f network will §cpair §f to the §bnext available §f tunnel of the same type — be careful with multi-network setups\n",
      "icon:10": {
        "Count:3": 1,
        "id:8": "appliedenergistics2:part",
        "Damage:2": 460,
        "OreDict:8": ""
      },
      "name:8": "P2P Tunnels",
      "visibility:8": "ALWAYS"
    }
  },
  "questID:3": 30195,
  "rewards:9": {},
  "tasks:9": {
    "0:10": {
      "autoConsume:1": 0,
      "consume:1": 0,
      "groupDetect:1": 0,
      "ignoreNBT:1": 0,
      "index:3": 0,
      "partialMatch:1": 0,
      "requiredItems:9": {
        "0:10": {
          "Count:3": 2,
          "id:8": "appliedenergistics2:part",
          "Damage:2": 460,
          "OreDict:8": ""
        },
        "1:10": {
          "Count:3": 1,
          "id:8": "appliedenergistics2:part",
          "Damage:2": 461,
          "OreDict:8": ""
        },
        "2:10": {
          "Count:3": 1,
          "id:8": "appliedenergistics2:part",
          "Damage:2": 462,
          "OreDict:8": ""
        },
        "3:10": {
          "Count:3": 1,
          "id:8": "appliedenergistics2:part",
          "Damage:2": 463,
          "OreDict:8": ""
        },
        "4:10": {
          "Count:3": 1,
          "id:8": "appliedenergistics2:part",
          "Damage:2": 467,
          "OreDict:8": ""
        },
        "5:10": {
          "Count:3": 1,
          "id:8": "appliedenergistics2:part",
          "Damage:2": 469,
          "OreDict:8": ""
        }
      },
      "taskID:8": "bq_standard:retrieval"
    }
  }
}
