{
  "questID:3": 40014,
  "preRequisites:11": [40013],
  "properties:10": {
    "betterquesting:10": {
      "desc:8": "§6Wood-Burning Generator§f\n\n§aThe simplest power source — burn anything burnable for early electricity.§f\n\nThe §bWood-Burning Generator§f is crafted at a crafting table, not the assembly. A cheap introduction to HE power.\n\n§6Crafting§f:\nSteel plates ×3, copper coils ×2, furnace, iron ingots at a crafting table.\n\n§6Operation§f:\nPlace fuel in the top slot, flip the switch. 100kHE internal buffer. Automatically stops when full — no wasted fuel. Fuel turns to ash periodically (clear the bottom slot).\n\n§6Bonuses§f:\n§b• Logs§f: +300% burn time\n§b• Wood§f: +100% burn time\n\n§6Fluid Mode§f:\nClick the arrow in GUI to burn flammable fluids instead. Note: 50% efficiency penalty vs dedicated fluid burners.\n\n§eTip§f: Your first power source. Upgrade to stirling engine or steam once you need more.",
      "icon:10": {
        "Count:3": 1,
        "id:8": "hbm:machine_wood_burner",
        "Damage:2": 0
      },
      "name:8": "Wood-Burning Generator",
      "visibility:8": "ALWAYS"
    }
  },
  "rewards:9": {},
  "tasks:9": {
    "0:10": {
      "autoConsume:1": 0,
      "consume:1": 0,
      "groupDetect:1": 0,
      "ignoreNBT:1": 0,
      "index:3": 0,
      "partialMatch:1": 0,
      "requiredItems:9": {
        "0:10": {
          "Count:3": 1,
          "id:8": "hbm:machine_wood_burner",
          "Damage:2": 0,
          "OreDict:8": ""
        }
      },
      "taskID:8": "bq_standard:retrieval"
    }
  }
}
