{
  "questID:3": 40056,
  "preRequisites:11": [40054],
  "properties:10": {
    "betterquesting:10": {
      "desc:8": "§6Machine Upgrades§f\n\n§aPlug-and-play buffs for most machines. Crafted at the Soldering Station (except Overdrive at Assembly Factory).§f\n\n§6Machine Upgrade Template§f (base item, craft first):\nCopper Wire + Polymer + Insulator + Integrated Circuit Board.\n\n§6Core Upgrades§f:\n§b• Speed Mk.I–III§f: ↓ process time, ↑ power. Max 3.\n§b• Effectiveness Mk.I–III§f: machine-dependent. Max 3.\n§b• Power Saving Mk.I–III§f: ↓ power, ↑ process time. Max 3.\n§b• Overdrive Mk.I–III§f: Highly ↓ time, highly ↑ power. Needs Saturnite + Assembly Factory.\n\n§6Specialized Upgrades§f:\n§b• Stack Ejection Mk.I–III§f: conveyors eject stacks.\n§b• Ejection Speed Mk.I–III§f: faster item ejection.\n§b• Emitter Health/Radius§f: forcefield HP and range.\n§b• 5G Radiation Emitter§f: turns Maxwell turret targets into Astolfo.\n§b• Afterburner Mk.I–III§f: Turbofan speed/knockback.\n\n§6Mining Laser Upgrades§f:\nCrystallizer, Shredder, Smelter, Scrap Destroyer, Screaming Scientist.\n\n§6Installation§f:\nOpen machine GUI, hover over the blue square (if present) to see compatible upgrades. Or search \"upgrade\" in JEI while the GUI is open.\n\n§eTip§f: Speed + Power Saving together can balance each other. Overdrive is for late-game only — it draws enormous power. Templates are consumed per upgrade, so craft extras.",
      "icon:10": {
        "Count:3": 1,
        "id:8": "hbm:upgrade_template",
        "Damage:2": 0
      },
      "name:8": "Machine Upgrades",
      "visibility:8": "ALWAYS"
    }
  },
  "rewards:9": {},
  "tasks:9": {
    "0:10": {
      "autoConsume:1": 0,
      "consume:1": 0,
      "groupDetect:1": 0,
      "ignoreNBT:1": 0,
      "index:3": 0,
      "partialMatch:1": 0,
      "requiredItems:9": {
        "0:10": {
          "Count:3": 1,
          "id:8": "hbm:upgrade_speed_1",
          "Damage:2": 0,
          "OreDict:8": ""
        }
      },
      "taskID:8": "bq_standard:retrieval"
    }
  }
}
