{
  "questID:3": 40200,
  "preRequisites:11": [
    40195
  ],
  "properties:10": {
    "betterquesting:10": {
      "desc:8": "§6Mustard Willow§f\n\n§aCultivate this alien-looking plant to produce cadmium — a vital alloying element!§f\n\nThe §bMustard Willow§f is a plant that grows near bedrock oil deposits. Its leaves can be harvested and processed into cadmium, which is mainly useful for making cadmium steel — a substitute for technetium steel.\n\n§6Growth Requirements§f:\n§b• Water§f — adjacent to the block below the plant (otherwise it won't grow at all)\n§b• Dead or Oily Dirt§f — plant must be on top of polluted soil to fully mature and drop leaves\n§b• No light required§f — grows in complete darkness\n\n§6Growth Stages§f (5 total):\n§b• Stage 2§f — needs §e1 extra block§f of space above to continue\n§b• Stage 4§f — consumes the dead/oily dirt underneath to mature\n§b• Stage 5§f — fully red and matured, top part yields §e3–6§f leaves + §e1§f plant item\n\n§6Automation§f: The plant can be harvested automatically with an §bAutomatic Buzz Saw§f, allowing the entire lifecycle to be fully automated. A §bFracking Tower§f continuously pollutes the ground, keeping mustard willow supplied with oily dirt.\n\n§6Processing§f:\n§b• Leaves§f → acidize with §e250 mB High-Performance Solvent§f in Ore Acidizer = §e1 Cadmium Powder§f per 10 leaves\n§b• Plant§f → liquifact in Industrial Liquefaction Machine = §e50 mB Ethanol§f\n\n§eTip§f: Check the in-game guide by hovering over the plant and pressing §bLSHIFT+F1§f!",
      "icon:10": {
        "Count:3": 1,
        "id:8": "hbm:plant_flower",
        "Damage:2": 2
      },
      "name:8": "Mustard Willow",
      "visibility:8": "ALWAYS"
    }
  },
  "tasks:9": {
    "0:10": {
      "requiredItems:9": {
        "0:10": {
          "Count:3": 1,
          "id:8": "hbm:plant_item",
          "Damage:2": 2,
          "OreDict:8": ""
        }
      },
      "taskID:8": "bq_standard:retrieval"
    }
  }
}
