{
  "preRequisites:11": [
    437
  ],
  "properties:10": {
    "betterquesting:10": {
      "desc:8": "§6Particle Chamber Detectors: Wire Chamber Detector§f\\n\\n§aWire Chamber Detectors track the path of charged particles inside a chamber!§f\\nThe §bWire Chamber Detector§f (`qmd:particle_chamber_detector:2`) is a detector tile placed inside a §bTarget Chamber§f, §bDecay Chamber§f, or §bCollision Chamber§f. When a charged particle beam passes through the detector, it triggers a §bparticle detection event§f that can be used for diagnostics or recipe progress in some QMD chamber recipes.\\n\\n§6Recipe§f:\\nPer the §bNC Infuser§f recipe (graph category `nuclearcraft_infuser`):\\n- Input: §bEmpty Wire Chamber§f (`qmd:part:7`, 1 unit)\\n- Output: §bWire Chamber Detector§f (`qmd:particle_chamber_detector:2`)\\n\\n§6Empty Wire Chamber Crafting§f:\\n- §bAdvanced Processor§f (`qmd:semiconductor:5`)\\n- §bBSCCO Superconducting Wire§f (`qmd:wireBSCCO`)\\n- §bPlatinum Ingot§f (`ingotPlatinum`)\\n- Other materials (see `QMDCraftingRecipeHandler.java` for the shaped recipe)\\n\\n§6Detector Family in QMD§f:\\n- §bSilicon Tracker Detector§f (`qmd:particle_chamber_detector:1`) — uses N-Type Doped Silicon\\n- §bWire Chamber Detector§f (`qmd:particle_chamber_detector:2`) — uses BSCCO wire + Advanced Processor\\n- §bBubble Chamber Detector§f (`qmd:particle_chamber_detector:0`) — uses Bubble Chamber fluid\\n\\n§6Use in Chambers§f:\\n- Detectors are placed as a §bchamber component§f (TileParticleChamberDetector) inside the multiblock interior.\\n- Some QMD chamber recipes require a specific detector tier to be present before the recipe can execute.\\n- Detectors contribute to the chamber's diagnostic readouts (track position, energy, particle ID).\\n\\n§eTip§f: Build at least one of each detector type for flexibility — some QMD chamber recipes (especially in the §bCollision Chamber§f) require specific detector types to function. The NC Infuser is the universal upgrader, so route it from your §bBasic Processor§f / §bAdvanced Processor§f production line.",
      "icon:10": {
        "Count:3": 1,
        "Damage:2": 2,
        "id:8": "qmd:particle_chamber_detector",
        "OreDict:8": ""
      },
      "name:8": "Particle Chamber Detectors"
    }
  },
  "questID:3": 440,
  "tasks:9": {
    "0:10": {
      "autoConsume:1": 1,
      "index:3": 0,
      "requiredItems:9": {
        "0:10": {
          "Count:3": 1,
          "Damage:2": 2,
          "id:8": "qmd:particle_chamber_detector",
          "OreDict:8": ""
        },
        "1:10": {
          "Count:3": 1,
          "Damage:2": 1,
          "id:8": "qmd:particle_chamber_detector",
          "OreDict:8": ""
        }
      },
      "taskID:8": "bq_standard:retrieval"
    }
  },
  "rewards:9": {}
}
